djangocms_qrcode/__init__.py
djangocms_qrcode/apps.py
djangocms_qrcode/cms_plugins.py
djangocms_qrcode/locale/cs/LC_MESSAGES/django.mo
djangocms_qrcode/locale/cs/LC_MESSAGES/django.po
djangocms_qrcode/migrations/0001_initial.py
djangocms_qrcode/migrations/0002_alter_qrcode_alignment_dark_and_more.py
djangocms_qrcode/migrations/__init__.py
djangocms_qrcode/models.py
djangocms_qrcode/templates/djangocms-qrcode.html
djangocms_qrcode-0.1.1.dist-info/LICENSE
djangocms_qrcode-0.1.1.dist-info/METADATA
djangocms_qrcode-0.1.1.dist-info/WHEEL
djangocms_qrcode-0.1.1.dist-info/RECORD
